sqlstrings/__init__.py
sqlstrings/csv_handling.py
sqlstrings/postgre.py
sqlstrings/transact.py
sqlstrings/value_handling.py
sqlstrings-0.1.4.dist-info/LICENSE.txt
sqlstrings-0.1.4.dist-info/METADATA
sqlstrings-0.1.4.dist-info/WHEEL
sqlstrings-0.1.4.dist-info/top_level.txt
sqlstrings-0.1.4.dist-info/RECORD
